<?xml version="1.0" encoding="UTF-8" standalone="no" ?>
<part_info part_name="XCV350-VSVD1760-2MP-E-S-ES1">

  <pins>

    <pin index="0"  name ="ddr4_c0_sysclk_p" iostandard="LVDS15" loc="AN35" />
    <pin index="1"  name ="ddr4_c0_sysclk_n" iostandard="LVDS15" loc="AN36" />	
	
    <pin index="2"  name ="ddr4_c1_sysclk_p" iostandard="LVDS15" loc="AT21" />
    <pin index="3"  name ="ddr4_c1_sysclk_n" iostandard="LVDS15" loc="AU20" />
	
    <pin index="4"  name ="ddr4_c2_sysclk_p" iostandard="LVDS15" loc="AP7" />
    <pin index="5"  name ="ddr4_c2_sysclk_n" iostandard="LVDS15" loc="AN6" />	
	
    <pin index="6"  name ="ddr4_c3_sysclk_p" iostandard="LVDS15" loc="R5" />
    <pin index="7"  name ="ddr4_c3_sysclk_n" iostandard="LVDS15" loc="P5" />	

	<pin index="100"  name ="c0_ddr4_act_n"      loc="AH32"/>
    <pin index="101"  name ="c0_ddr4_adr0"       loc="AG33"/>
    <pin index="102"  name ="c0_ddr4_adr1"       loc="AE34"/>
    <pin index="103"  name ="c0_ddr4_adr2"       loc="AD34"/>
	<pin index="104"  name ="c0_ddr4_adr3"       loc="AJ33"/>
    <pin index="105"  name ="c0_ddr4_adr4"       loc="AF35"/>
    <pin index="106"  name ="c0_ddr4_adr5"       loc="AH36"/>
    <pin index="107"  name ="c0_ddr4_adr6"       loc="AF36"/>
    <pin index="108"  name ="c0_ddr4_adr7"       loc="AG38"/>
    <pin index="109"  name ="c0_ddr4_adr8"       loc="AD37"/>
    <pin index="110"  name ="c0_ddr4_adr9"       loc="AE32"/>
    <pin index="111"  name ="c0_ddr4_adr10"      loc="AJ31"/>
    <pin index="112"  name ="c0_ddr4_adr11"      loc="AE36"/>
    <pin index="113"  name ="c0_ddr4_adr12"      loc="AG40"/>
    <pin index="114"  name ="c0_ddr4_adr13"      loc="AF37"/>
    <pin index="115"  name ="c0_ddr4_adr14"      loc="AK35"/>
    <pin index="116"  name ="c0_ddr4_adr15"      loc="AH35"/>
    <pin index="117"  name ="c0_ddr4_adr16"      loc="AE33"/>
    <pin index="118"  name ="c0_ddr4_ba0"        loc="AK33"/>
    <pin index="119"  name ="c0_ddr4_ba1"        loc="AF34"/>
    <pin index="120"  name ="c0_ddr4_bg0"        loc="AK32"/>
    <pin index="121"  name ="c0_ddr4_ck_c0"      loc="AG35"/>
    <pin index="122"  name ="c0_ddr4_ck_t0"      loc="AH34"/>
    <pin index="123"  name ="c0_ddr4_cke0"       loc="AF32"/>
	<pin index="124"  name ="c0_ddr4_cs0_n"      loc="AJ34"/>
    <pin index="125"  name ="c0_ddr4_dq0"        loc="AJ39"/>
    <pin index="126"  name ="c0_ddr4_dq1"        loc="AF38"/>
    <pin index="127"  name ="c0_ddr4_dq2"        loc="AJ38"/>
	<pin index="128"  name ="c0_ddr4_dq3"        loc="AE39"/>
    <pin index="129"  name ="c0_ddr4_dq4"        loc="AK37"/>
    <pin index="130"  name ="c0_ddr4_dq5"        loc="AD39"/>
    <pin index="131"  name ="c0_ddr4_dq6"        loc="AJ40"/>
    <pin index="132"  name ="c0_ddr4_dq7"        loc="AD38"/>
    <pin index="133"  name ="c0_ddr4_dq8"        loc="AJ42"/>
    <pin index="134"  name ="c0_ddr4_dq9"        loc="AE42"/>
	<pin index="135"  name ="c0_ddr4_dq10"       loc="AH40"/>
    <pin index="136"  name ="c0_ddr4_dq11"       loc="AF42"/>
    <pin index="137"  name ="c0_ddr4_dq12"       loc="AK42"/>
    <pin index="138"  name ="c0_ddr4_dq13"       loc="AE41"/>
    <pin index="139"  name ="c0_ddr4_dq14"       loc="AH41"/>
    <pin index="140"  name ="c0_ddr4_dq15"       loc="AE40"/>
    <pin index="141"  name ="c0_ddr4_dq16"       loc="AN32"/>
    <pin index="142"  name ="c0_ddr4_dq17"       loc="AM31"/>
    <pin index="143"  name ="c0_ddr4_dq18"       loc="AM36"/>
    <pin index="144"  name ="c0_ddr4_dq19"       loc="AL31"/>
    <pin index="145"  name ="c0_ddr4_dq20"       loc="AN31"/>
    <pin index="146"  name ="c0_ddr4_dq21"       loc="AM30"/>
    <pin index="147"  name ="c0_ddr4_dq22"       loc="AM35"/>
    <pin index="148"  name ="c0_ddr4_dq23"       loc="AN33"/>
    <pin index="149"  name ="c0_ddr4_dq24"       loc="AL41"/>
    <pin index="150"  name ="c0_ddr4_dq25"       loc="AL38"/>
    <pin index="151"  name ="c0_ddr4_dq26"       loc="AM41"/>
    <pin index="152"  name ="c0_ddr4_dq27"       loc="AK41"/>
    <pin index="153"  name ="c0_ddr4_dq28"       loc="AM39"/>
    <pin index="154"  name ="c0_ddr4_dq29"       loc="AM38"/>
    <pin index="155"  name ="c0_ddr4_dq30"       loc="AL42"/>
    <pin index="156"  name ="c0_ddr4_dq31"       loc="AL39"/>
    <pin index="157"  name ="c0_ddr4_dq32"       loc="AR42"/>
    <pin index="158"  name ="c0_ddr4_dq33"       loc="AN38"/>
	<pin index="159"  name ="c0_ddr4_dq34"       loc="AP39"/>
    <pin index="160"  name ="c0_ddr4_dq35"       loc="AP38"/>
    <pin index="161"  name ="c0_ddr4_dq36"       loc="AR40"/>
    <pin index="162"  name ="c0_ddr4_dq37"       loc="AR39"/>
    <pin index="163"  name ="c0_ddr4_dq38"       loc="AR41"/>
    <pin index="164"  name ="c0_ddr4_dq39"       loc="AT39"/>
    <pin index="165"  name ="c0_ddr4_dq40"       loc="AT34"/>
    <pin index="166"  name ="c0_ddr4_dq41"       loc="AP31"/>
    <pin index="167"  name ="c0_ddr4_dq42"       loc="AR35"/>
    <pin index="168"  name ="c0_ddr4_dq43"       loc="AR32"/>
    <pin index="169"  name ="c0_ddr4_dq44"       loc="AT35"/>
    <pin index="170"  name ="c0_ddr4_dq45"       loc="AR31"/>
    <pin index="171"  name ="c0_ddr4_dq46"       loc="AP35"/>
    <pin index="172"  name ="c0_ddr4_dq47"       loc="AT31"/>
    <pin index="173"  name ="c0_ddr4_dq48"       loc="BA41"/>
    <pin index="174"  name ="c0_ddr4_dq49"       loc="AU41"/>
    <pin index="175"  name ="c0_ddr4_dq50"       loc="AY42"/>
    <pin index="176"  name ="c0_ddr4_dq51"       loc="AT42"/>
    <pin index="177"  name ="c0_ddr4_dq52"       loc="BB40"/>
    <pin index="178"  name ="c0_ddr4_dq53"       loc="AT41"/>
    <pin index="179"  name ="c0_ddr4_dq54"       loc="AY41"/>
    <pin index="180"  name ="c0_ddr4_dq55"       loc="AV42"/>
    <pin index="181"  name ="c0_ddr4_dq56"       loc="BA38"/>
    <pin index="182"  name ="c0_ddr4_dq57"       loc="AU39"/>
    <pin index="183"  name ="c0_ddr4_dq58"       loc="BA39"/>
    <pin index="184"  name ="c0_ddr4_dq59"       loc="AU38"/>
    <pin index="185"  name ="c0_ddr4_dq60"       loc="BB38"/>
    <pin index="186"  name ="c0_ddr4_dq61"       loc="AU40"/>
    <pin index="187"  name ="c0_ddr4_dq62"       loc="BB39"/>
    <pin index="188"  name ="c0_ddr4_dq63"       loc="AV40"/>
    <pin index="189"  name ="c0_ddr4_dq64"       loc="BB34"/>
    <pin index="190"  name ="c0_ddr4_dq65"       loc="AU33"/>
    <pin index="191"  name ="c0_ddr4_dq66"       loc="BA34"/>
    <pin index="192"  name ="c0_ddr4_dq67"       loc="AV35"/>
    <pin index="193"  name ="c0_ddr4_dq68"       loc="BA33"/>
    <pin index="194"  name ="c0_ddr4_dq69"       loc="AU35"/>
    <pin index="195"  name ="c0_ddr4_dq70"       loc="BB35"/>
    <pin index="196"  name ="c0_ddr4_dq71"       loc="AV33"/>
	<pin index="197"  name ="c0_ddr4_dqs_c0"     loc="AG39"/>
	<pin index="198"  name ="c0_ddr4_dqs_c1"     loc="AG41"/>
	<pin index="199"  name ="c0_ddr4_dqs_c2"     loc="AM34"/>
	<pin index="200"  name ="c0_ddr4_dqs_c3"     loc="AK40"/>
	<pin index="201"  name ="c0_ddr4_dqs_c4"     loc="AP40"/>
	<pin index="202"  name ="c0_ddr4_dqs_c5"     loc="AP33"/>
	<pin index="203"  name ="c0_ddr4_dqs_c6"     loc="AW42"/>
	<pin index="204"  name ="c0_ddr4_dqs_c7"     loc="AW38"/>
	<pin index="205"  name ="c0_ddr4_dqs_c8"     loc="AY34"/>
    <pin index="206"  name ="c0_ddr4_dqs_t0"     loc="AH38"/>
    <pin index="207"  name ="c0_ddr4_dqs_t1"     loc="AH42"/>
    <pin index="208"  name ="c0_ddr4_dqs_t2"     loc="AL35"/>
    <pin index="209"  name ="c0_ddr4_dqs_t3"     loc="AK39"/>
    <pin index="210"  name ="c0_ddr4_dqs_t4"     loc="AN40"/>
	<pin index="211"  name ="c0_ddr4_dqs_t5"     loc="AP34"/>
	<pin index="212"  name ="c0_ddr4_dqs_t6"     loc="AV41"/>
	<pin index="213"  name ="c0_ddr4_dqs_t7"     loc="AY39"/>
	<pin index="214"  name ="c0_ddr4_dqs_t8"     loc="AY35"/>
	<pin index="215"  name ="c0_ddr4_dm_dbi_n0"  loc="AF39"/>
    <pin index="216"  name ="c0_ddr4_dm_dbi_n1"  loc="AF41"/>
	<pin index="217"  name ="c0_ddr4_dm_dbi_n2"  loc="AL32"/>
    <pin index="218"  name ="c0_ddr4_dm_dbi_n3"  loc="AM40"/>
	<pin index="219"  name ="c0_ddr4_dm_dbi_n4"  loc="AP42"/>
    <pin index="220"  name ="c0_ddr4_dm_dbi_n5"  loc="AT33"/>
	<pin index="221"  name ="c0_ddr4_dm_dbi_n6"  loc="AY40"/>
    <pin index="222"  name ="c0_ddr4_dm_dbi_n7"  loc="AV38"/>
	<pin index="223"  name ="c0_ddr4_dm_dbi_n8"  loc="AW34"/>
    <pin index="224"  name ="c0_ddr4_odt0"       loc="AF33"/>
    <pin index="225"  name ="c0_ddr4_reset_n"    loc="AL37" iostandard="LVCMOS12" drive="8"/>
	<pin index="226"  name ="c0_ddr4_parity"     loc="AD36"/>
	<pin index="227"  name ="c0_ddr4_alert_n"    loc="AM37"/>	

	
	<!-- <pin index="300"  name ="c1_ddr4_act_n"      loc="AU21"/> -->
	<pin index="300"  name ="c1_ddr4_act_n"      loc="AJ27"/>
	
    <pin index="301"  name ="c1_ddr4_adr0"       loc="AH26"/>
    <pin index="302"  name ="c1_ddr4_adr1"       loc="AN29"/>
    <pin index="303"  name ="c1_ddr4_adr2"       loc="AM28"/>
	<pin index="304"  name ="c1_ddr4_adr3"       loc="AK26"/>
	<pin index="305"  name ="c1_ddr4_adr4"       loc="AN28"/>
	<pin index="306"  name ="c1_ddr4_adr5"       loc="AR27"/>
    <pin index="307"  name ="c1_ddr4_adr6"       loc="AR28"/>
    <pin index="308"  name ="c1_ddr4_adr7"       loc="AW28"/>
    <pin index="309"  name ="c1_ddr4_adr8"       loc="AT30"/>
    <pin index="310"  name ="c1_ddr4_adr9"       loc="AJ28"/>
    <pin index="311"  name ="c1_ddr4_adr10"      loc="AK27"/>
    <pin index="312"  name ="c1_ddr4_adr11"      loc="AR29"/>
    <pin index="313"  name ="c1_ddr4_adr12"      loc="BB28"/>
    <pin index="314"  name ="c1_ddr4_adr13"      loc="AT29"/>
    <pin index="315"  name ="c1_ddr4_adr14"      loc="AN25"/>
	<pin index="316"  name ="c1_ddr4_adr15"      loc="AP25"/>
    <pin index="317"  name ="c1_ddr4_adr16"      loc="AK29"/>
    <pin index="318"  name ="c1_ddr4_ba0"        loc="AL25"/>
    <pin index="319"  name ="c1_ddr4_ba1"        loc="AP27"/>
    <pin index="320"  name ="c1_ddr4_bg0"        loc="AL26"/>
    <pin index="321"  name ="c1_ddr4_ck_c0"      loc="AN27"/>
    <pin index="322"  name ="c1_ddr4_ck_t0"      loc="AM27"/>
    <pin index="323"  name ="c1_ddr4_cke0"       loc="AL29"/>
	<pin index="324"  name ="c1_ddr4_cs0_n"      loc="AP26"/>
    <pin index="325"  name ="c1_ddr4_dq0"        loc="BB26"/>
    <pin index="326"  name ="c1_ddr4_dq1"        loc="BB30"/>
    <pin index="327"  name ="c1_ddr4_dq2"        loc="BA27"/>
    <pin index="328"  name ="c1_ddr4_dq3"        loc="AY29"/>
	<pin index="329"  name ="c1_ddr4_dq4"        loc="AY26"/>
	<pin index="330"  name ="c1_ddr4_dq5"        loc="AY30"/>
    <pin index="331"  name ="c1_ddr4_dq6"        loc="BA26"/>
    <pin index="332"  name ="c1_ddr4_dq7"        loc="BB29"/>
    <pin index="333"  name ="c1_ddr4_dq8"        loc="AV27"/>
    <pin index="334"  name ="c1_ddr4_dq9"        loc="AV30"/>
	
	<pin index="335"  name ="c1_ddr4_dq10"       loc="AU25"/>
    <pin index="336"  name ="c1_ddr4_dq11"       loc="AW30"/>
    <pin index="337"  name ="c1_ddr4_dq12"       loc="AW27"/>
    <pin index="338"  name ="c1_ddr4_dq13"       loc="AW29"/>
    <pin index="339"  name ="c1_ddr4_dq14"       loc="AV26"/>
    <pin index="340"  name ="c1_ddr4_dq15"       loc="AU29"/>
    <pin index="341"  name ="c1_ddr4_dq16"       loc="AK23"/>
    <pin index="342"  name ="c1_ddr4_dq17"       loc="AR24"/>
    <pin index="343"  name ="c1_ddr4_dq18"       loc="AP23"/>
    <pin index="344"  name ="c1_ddr4_dq19"       loc="AH22"/>
    <pin index="345"  name ="c1_ddr4_dq20"       loc="AJ22"/>
    <pin index="346"  name ="c1_ddr4_dq21"       loc="AJ24"/>
    <pin index="347"  name ="c1_ddr4_dq22"       loc="AN23"/>
    <pin index="348"  name ="c1_ddr4_dq23"       loc="AR23"/>
    <pin index="349"  name ="c1_ddr4_dq24"       loc="BB24"/>
    <pin index="350"  name ="c1_ddr4_dq25"       loc="AW23"/>
    <pin index="351"  name ="c1_ddr4_dq26"       loc="AY24"/>
    <pin index="352"  name ="c1_ddr4_dq27"       loc="BB25"/>
    <pin index="353"  name ="c1_ddr4_dq28"       loc="BA24"/>
    <pin index="354"  name ="c1_ddr4_dq29"       loc="AV25"/>
    <pin index="355"  name ="c1_ddr4_dq30"       loc="AW24"/>
    <pin index="356"  name ="c1_ddr4_dq31"       loc="AU24"/>
    <pin index="357"  name ="c1_ddr4_dq32"       loc="BA21"/>
    <pin index="358"  name ="c1_ddr4_dq33"       loc="AV21"/>
	<pin index="359"  name ="c1_ddr4_dq34"       loc="AV20"/>
    <pin index="360"  name ="c1_ddr4_dq35"       loc="BA22"/>
    <pin index="361"  name ="c1_ddr4_dq36"       loc="BB21"/>
    <pin index="362"  name ="c1_ddr4_dq37"       loc="AW22"/>
    <pin index="363"  name ="c1_ddr4_dq38"       loc="BB20"/>
    <pin index="364"  name ="c1_ddr4_dq39"       loc="AV22"/>
    <pin index="365"  name ="c1_ddr4_dq40"       loc="AP21"/>
    <pin index="366"  name ="c1_ddr4_dq41"       loc="AL22"/>
    <pin index="367"  name ="c1_ddr4_dq42"       loc="AL20"/>
    <pin index="368"  name ="c1_ddr4_dq43"       loc="AK21"/>
    <pin index="369"  name ="c1_ddr4_dq44"       loc="AK20"/>
    <pin index="370"  name ="c1_ddr4_dq45"       loc="AJ21"/>
    <pin index="371"  name ="c1_ddr4_dq46"       loc="AN20"/>
    <pin index="372"  name ="c1_ddr4_dq47"       loc="AH20"/>
    <pin index="373"  name ="c1_ddr4_dq48"       loc="BB19"/>
    <pin index="374"  name ="c1_ddr4_dq49"       loc="BA16"/>
    <pin index="375"  name ="c1_ddr4_dq50"       loc="AY19"/>
    <pin index="376"  name ="c1_ddr4_dq51"       loc="BB16"/>
    <pin index="377"  name ="c1_ddr4_dq52"       loc="BA19"/>
    <pin index="378"  name ="c1_ddr4_dq53"       loc="BB15"/>
    <pin index="379"  name ="c1_ddr4_dq54"       loc="BA18"/>
    <pin index="380"  name ="c1_ddr4_dq55"       loc="AY15"/>
    <pin index="381"  name ="c1_ddr4_dq56"       loc="AV18"/>
    <pin index="382"  name ="c1_ddr4_dq57"       loc="AU16"/>
    <pin index="383"  name ="c1_ddr4_dq58"       loc="AW19"/>
    <pin index="384"  name ="c1_ddr4_dq59"       loc="AU19"/>
    <pin index="385"  name ="c1_ddr4_dq60"       loc="AW18"/>
    <pin index="386"  name ="c1_ddr4_dq61"       loc="AW15"/>
    <pin index="387"  name ="c1_ddr4_dq62"       loc="AU15"/>
    <pin index="388"  name ="c1_ddr4_dq63"       loc="AV15"/>
    <pin index="389"  name ="c1_ddr4_dq64"       loc="AN16"/>
    <pin index="390"  name ="c1_ddr4_dq65"       loc="AM18"/>
    <pin index="391"  name ="c1_ddr4_dq66"       loc="AP15"/>
    <pin index="392"  name ="c1_ddr4_dq67"       loc="AM19"/>
    <pin index="393"  name ="c1_ddr4_dq68"       loc="AN15"/>
    <pin index="394"  name ="c1_ddr4_dq69"       loc="AN19"/>
    <pin index="395"  name ="c1_ddr4_dq70"       loc="AM15"/>
    <pin index="396"  name ="c1_ddr4_dq71"       loc="AL19"/>
	<pin index="397"  name ="c1_ddr4_dqs_c0"     loc="BA28"/>
	<pin index="398"  name ="c1_ddr4_dqs_c1"     loc="AU28"/>
	<pin index="399"  name ="c1_ddr4_dqs_c2"     loc="AM24"/>
	<pin index="400"  name ="c1_ddr4_dqs_c3"     loc="AY25"/>
	<pin index="401"  name ="c1_ddr4_dqs_c4"     loc="AW20"/>
	<pin index="402"  name ="c1_ddr4_dqs_c5"     loc="AP22"/>
	<pin index="403"  name ="c1_ddr4_dqs_c6"     loc="BA17"/>
	<pin index="404"  name ="c1_ddr4_dqs_c7"     loc="AU17"/>
	<pin index="405"  name ="c1_ddr4_dqs_c8"     loc="AN17"/>
    <pin index="406"  name ="c1_ddr4_dqs_t0"     loc="AY27"/>
    <pin index="407"  name ="c1_ddr4_dqs_t1"     loc="AU27"/>
    <pin index="408"  name ="c1_ddr4_dqs_t2"     loc="AN24"/>
    <pin index="409"  name ="c1_ddr4_dqs_t3"     loc="AW25"/>
    <pin index="410"  name ="c1_ddr4_dqs_t4"     loc="AY20"/>
	<pin index="411"  name ="c1_ddr4_dqs_t5"     loc="AN21"/>
	<pin index="412"  name ="c1_ddr4_dqs_t6"     loc="BB18"/>
	<pin index="413"  name ="c1_ddr4_dqs_t7"     loc="AV16"/>
	<pin index="414"  name ="c1_ddr4_dqs_t8"     loc="AM16"/>
	<pin index="415"  name ="c1_ddr4_dm_dbi_n0"  loc="BA29"/>
    <pin index="416"  name ="c1_ddr4_dm_dbi_n1"  loc="AV28"/>
	<pin index="417"  name ="c1_ddr4_dm_dbi_n2"  loc="AK24"/>
    <pin index="418"  name ="c1_ddr4_dm_dbi_n3"  loc="BA23"/>
	<pin index="419"  name ="c1_ddr4_dm_dbi_n4"  loc="AY21"/>
    <pin index="420"  name ="c1_ddr4_dm_dbi_n5"  loc="AM22"/>
	<pin index="421"  name ="c1_ddr4_dm_dbi_n6"  loc="AY16"/>
    <pin index="422"  name ="c1_ddr4_dm_dbi_n7"  loc="AW17"/>
	<pin index="423"  name ="c1_ddr4_dm_dbi_n8"  loc="AP18"/>
    <pin index="424"  name ="c1_ddr4_odt0"       loc="AL28"/>
    <pin index="425"  name ="c1_ddr4_reset_n"    loc="AT22"  iostandard="LVCMOS12"   drive="8"/>
	<pin index="426"  name ="c1_ddr4_parity"     loc="AP29"/>
	<pin index="427"  name ="c1_ddr4_alert_n"    loc="AU21"/>

	<pin index="500"  name ="c2_ddr4_act_n"      loc="AY12"/>
    <pin index="501"  name ="c2_ddr4_adr0"       loc="BA12"/>
    <pin index="502"  name ="c2_ddr4_adr1"       loc="BA9" />
    <pin index="503"  name ="c2_ddr4_adr2"       loc="BB9" />
    <pin index="504"  name ="c2_ddr4_adr3"       loc="AW13"/>
    <pin index="505"  name ="c2_ddr4_adr4"       loc="BA11"/>
    <pin index="506"  name ="c2_ddr4_adr5"       loc="AV8"/>
    <pin index="507"  name ="c2_ddr4_adr6"       loc="AW8"/>
    <pin index="508"  name ="c2_ddr4_adr7"       loc="BA4"/>
    <pin index="509"  name ="c2_ddr4_adr8"       loc="AY7"/>
    <pin index="510"  name ="c2_ddr4_adr9"       loc="BB14"/>
    <pin index="511"  name ="c2_ddr4_adr10"      loc="AY14"/>
    <pin index="512"  name ="c2_ddr4_adr11"      loc="BA7"/>
    <pin index="513"  name ="c2_ddr4_adr12"      loc="AW3"/>
    <pin index="514"  name ="c2_ddr4_adr13"      loc="AW7"/>
    <pin index="515"  name ="c2_ddr4_adr14"      loc="AV10"/>
    <pin index="516"  name ="c2_ddr4_adr15"      loc="AW9"/>
    <pin index="517"  name ="c2_ddr4_adr16"      loc="BB13"/>
    <pin index="518"  name ="c2_ddr4_ba0"        loc="AW12"/>
    <pin index="519"  name ="c2_ddr4_ba1"        loc="AY11"/>
    <pin index="520"  name ="c2_ddr4_bg0"        loc="AW14"/>
    <pin index="521"  name ="c2_ddr4_ck_c0"      loc="AY9"/>
    <pin index="522"  name ="c2_ddr4_ck_t0"      loc="AY10"/>
    <pin index="523"  name ="c2_ddr4_cke0"       loc="BA14"/>
	<pin index="524"  name ="c2_ddr4_cs0_n"      loc="AW10"/>
    <pin index="525"  name ="c2_ddr4_dq0"        loc="AV5"/>
    <pin index="526"  name ="c2_ddr4_dq1"        loc="AW5"/>
    <pin index="527"  name ="c2_ddr4_dq2"        loc="BB4"/>
    <pin index="528"  name ="c2_ddr4_dq3"        loc="BA6"/>
    <pin index="529"  name ="c2_ddr4_dq4"        loc="AU4"/>
    <pin index="530"  name ="c2_ddr4_dq5"        loc="AV6"/>
    <pin index="531"  name ="c2_ddr4_dq6"        loc="BB5"/>
    <pin index="532"  name ="c2_ddr4_dq7"        loc="AY6"/>
    <pin index="533"  name ="c2_ddr4_dq8"        loc="BA2"/>
    <pin index="534"  name ="c2_ddr4_dq9"        loc="AV3"/>
	<pin index="535"  name ="c2_ddr4_dq10"       loc="AY1"/>
    <pin index="536"  name ="c2_ddr4_dq11"       loc="BB3"/>
    <pin index="537"  name ="c2_ddr4_dq12"       loc="AU1"/>
    <pin index="538"  name ="c2_ddr4_dq13"       loc="AU3"/>
    <pin index="539"  name ="c2_ddr4_dq14"       loc="AV2"/>
    <pin index="540"  name ="c2_ddr4_dq15"       loc="BA3"/>
    <pin index="541"  name ="c2_ddr4_dq16"       loc="AU13"/>
    <pin index="542"  name ="c2_ddr4_dq17"       loc="AR9"/>
    <pin index="543"  name ="c2_ddr4_dq18"       loc="AU12"/>
    <pin index="544"  name ="c2_ddr4_dq19"       loc="AT9"/>
    <pin index="545"  name ="c2_ddr4_dq20"       loc="AT14"/>
    <pin index="546"  name ="c2_ddr4_dq21"       loc="AU8"/>
    <pin index="547"  name ="c2_ddr4_dq22"       loc="AT13"/>
    <pin index="548"  name ="c2_ddr4_dq23"       loc="AU9"/>
    <pin index="549"  name ="c2_ddr4_dq24"       loc="AT2"/>
    <pin index="550"  name ="c2_ddr4_dq25"       loc="AT6"/>
    <pin index="551"  name ="c2_ddr4_dq26"       loc="AT1"/>
    <pin index="552"  name ="c2_ddr4_dq27"       loc="AR6"/>
    <pin index="553"  name ="c2_ddr4_dq28"       loc="AR1"/>
    <pin index="554"  name ="c2_ddr4_dq29"       loc="AU5"/>
    <pin index="555"  name ="c2_ddr4_dq30"       loc="AR2"/>
    <pin index="556"  name ="c2_ddr4_dq31"       loc="AU6"/>
    <pin index="557"  name ="c2_ddr4_dq32"       loc="AN2"/>
    <pin index="558"  name ="c2_ddr4_dq33"       loc="AN5"/>
	<pin index="559"  name ="c2_ddr4_dq34"       loc="AP4"/>
    <pin index="560"  name ="c2_ddr4_dq35"       loc="AP5"/>
    <pin index="561"  name ="c2_ddr4_dq36"       loc="AP2"/>
    <pin index="562"  name ="c2_ddr4_dq37"       loc="AM5"/>
    <pin index="563"  name ="c2_ddr4_dq38"       loc="AM1"/>
    <pin index="564"  name ="c2_ddr4_dq39"       loc="AN1"/>
    <pin index="565"  name ="c2_ddr4_dq40"       loc="AM10"/>
    <pin index="566"  name ="c2_ddr4_dq41"       loc="AN12"/>
    <pin index="567"  name ="c2_ddr4_dq42"       loc="AN9"/>
    <pin index="568"  name ="c2_ddr4_dq43"       loc="AN11"/>
    <pin index="569"  name ="c2_ddr4_dq44"       loc="AN13"/>
    <pin index="570"  name ="c2_ddr4_dq45"       loc="AP13"/>
    <pin index="571"  name ="c2_ddr4_dq46"       loc="AP14"/>
    <pin index="572"  name ="c2_ddr4_dq47"       loc="AR13"/>
    <pin index="573"  name ="c2_ddr4_dq48"       loc="AK2"/>
    <pin index="574"  name ="c2_ddr4_dq49"       loc="AF2"/>
    <pin index="575"  name ="c2_ddr4_dq50"       loc="AK1"/>
    <pin index="576"  name ="c2_ddr4_dq51"       loc="AG3"/>
    <pin index="577"  name ="c2_ddr4_dq52"       loc="AL1"/>
    <pin index="578"  name ="c2_ddr4_dq53"       loc="AF3"/>
    <pin index="579"  name ="c2_ddr4_dq54"       loc="AL2"/>
    <pin index="580"  name ="c2_ddr4_dq55"       loc="AF1"/>
    <pin index="581"  name ="c2_ddr4_dq56"       loc="AL4"/>
    <pin index="582"  name ="c2_ddr4_dq57"       loc="AG4"/>
    <pin index="583"  name ="c2_ddr4_dq58"       loc="AK4"/>
    <pin index="584"  name ="c2_ddr4_dq59"       loc="AH5"/>
    <pin index="585"  name ="c2_ddr4_dq60"       loc="AL3"/>
    <pin index="586"  name ="c2_ddr4_dq61"       loc="AG6"/>
    <pin index="587"  name ="c2_ddr4_dq62"       loc="AK5"/>
    <pin index="588"  name ="c2_ddr4_dq63"       loc="AG5"/>
    <pin index="589"  name ="c2_ddr4_dq64"       loc="AL10"/>
    <pin index="590"  name ="c2_ddr4_dq65"       loc="AG11"/>
    <pin index="591"  name ="c2_ddr4_dq66"       loc="AK11"/>
    <pin index="592"  name ="c2_ddr4_dq67"       loc="AK9"/>
    <pin index="593"  name ="c2_ddr4_dq68"       loc="AH10"/>
    <pin index="594"  name ="c2_ddr4_dq69"       loc="AH8"/>
    <pin index="595"  name ="c2_ddr4_dq70"       loc="AL9"/>
    <pin index="596"  name ="c2_ddr4_dq71"       loc="AG9"/>
	<pin index="597"  name ="c2_ddr4_dqs_c0"     loc="AY4"/>
	<pin index="598"  name ="c2_ddr4_dqs_c1"     loc="AW2"/>
	<pin index="599"  name ="c2_ddr4_dqs_c2"     loc="AT10"/>
	<pin index="600"  name ="c2_ddr4_dqs_c3"     loc="AT4"/>
	<pin index="601"  name ="c2_ddr4_dqs_c4"     loc="AM3"/>
	<pin index="602"  name ="c2_ddr4_dqs_c5"     loc="AP10"/>
	<pin index="603"  name ="c2_ddr4_dqs_c6"     loc="AH1"/>
	<pin index="604"  name ="c2_ddr4_dqs_c7"     loc="AJ3"/>
	<pin index="605"  name ="c2_ddr4_dqs_c8"     loc="AJ10"/>
    <pin index="606"  name ="c2_ddr4_dqs_t0"     loc="AW4"/>
    <pin index="607"  name ="c2_ddr4_dqs_t1"     loc="AV1"/>
    <pin index="608"  name ="c2_ddr4_dqs_t2"     loc="AR11"/>
    <pin index="609"  name ="c2_ddr4_dqs_t3"     loc="AR5"/>
    <pin index="610"  name ="c2_ddr4_dqs_t4"     loc="AM4"/>
	<pin index="611"  name ="c2_ddr4_dqs_t5"     loc="AP9"/>
	<pin index="612"  name ="c2_ddr4_dqs_t6"     loc="AJ2"/>
	<pin index="613"  name ="c2_ddr4_dqs_t7"     loc="AH3"/>
	<pin index="614"  name ="c2_ddr4_dqs_t8"     loc="AH11"/>
	<pin index="615"  name ="c2_ddr4_dm_dbi_n0"  loc="AY5"/>
    <pin index="616"  name ="c2_ddr4_dm_dbi_n1"  loc="AY2"/>
	<pin index="617"  name ="c2_ddr4_dm_dbi_n2"  loc="AU11"/>
    <pin index="618"  name ="c2_ddr4_dm_dbi_n3"  loc="AT3"/>
	<pin index="619"  name ="c2_ddr4_dm_dbi_n4"  loc="AN3"/>
    <pin index="620"  name ="c2_ddr4_dm_dbi_n5"  loc="AR12"/>
	<pin index="621"  name ="c2_ddr4_dm_dbi_n6"  loc="AG1"/>
    <pin index="622"  name ="c2_ddr4_dm_dbi_n7"  loc="AJ5"/>
	<pin index="623"  name ="c2_ddr4_dm_dbi_n8"  loc="AJ9"/>
    <pin index="624"  name ="c2_ddr4_odt0"       loc="BA13"/>
    <pin index="625"  name ="c2_ddr4_reset_n"    loc="AT7"  iostandard="LVCMOS12"   drive="8"/>
	<pin index="626"  name ="c2_ddr4_parity"     loc="BB10"/>
	<pin index="627"  name ="c2_ddr4_alert_n"    loc="AR7"/>	

	<pin index="700"  name ="c3_ddr4_act_n"      loc="AD12"/>
    <pin index="701"  name ="c3_ddr4_adr0"       loc="AD11"/>
    <pin index="702"  name ="c3_ddr4_adr1"       loc="AE9"/>
    <pin index="703"  name ="c3_ddr4_adr2"       loc="AE10"/>
    <pin index="704"  name ="c3_ddr4_adr3"       loc="AB11"/>
    <pin index="705"  name ="c3_ddr4_adr4"       loc="AD8"/>
    <pin index="706"  name ="c3_ddr4_adr5"       loc="AB7"/>
    <pin index="707"  name ="c3_ddr4_adr6"       loc="AC7"/>
    <pin index="708"  name ="c3_ddr4_adr7"       loc="AC5"/>
    <pin index="709"  name ="c3_ddr4_adr8"       loc="AE6"/>
    <pin index="710"  name ="c3_ddr4_adr9"       loc="AF12"/>
    <pin index="711"  name ="c3_ddr4_adr10"      loc="AC12"/>
    <pin index="712"  name ="c3_ddr4_adr11"      loc="AE7"/>
    <pin index="713"  name ="c3_ddr4_adr12"      loc="AC1"/>
    <pin index="714"  name ="c3_ddr4_adr13"      loc="AC6"/>
    <pin index="715"  name ="c3_ddr4_adr14"      loc="AA8"/>
    <pin index="716"  name ="c3_ddr4_adr15"      loc="AB9"/>
    <pin index="717"  name ="c3_ddr4_adr16"      loc="AE11"/>
    <pin index="718"  name ="c3_ddr4_ba0"        loc="AA11"/>
    <pin index="719"  name ="c3_ddr4_ba1"        loc="AC8"/>
    <pin index="720"  name ="c3_ddr4_bg0"        loc="AC13"/>
    <pin index="721"  name ="c3_ddr4_ck_c0"      loc="AC9"/>
    <pin index="722"  name ="c3_ddr4_ck_t0"      loc="AC10"/>
    <pin index="723"  name ="c3_ddr4_cke0"       loc="AF13"/>
	<pin index="724"  name ="c3_ddr4_cs0_n"      loc="AB10"/>
    <pin index="725"  name ="c3_ddr4_dq0"        loc="V9"/>
    <pin index="726"  name ="c3_ddr4_dq1"        loc="V7"/>
    <pin index="727"  name ="c3_ddr4_dq2"        loc="U5"/>
    <pin index="728"  name ="c3_ddr4_dq3"        loc="W5"/>
    <pin index="729"  name ="c3_ddr4_dq4"        loc="U9"/>
    <pin index="730"  name ="c3_ddr4_dq5"        loc="V6"/>
    <pin index="731"  name ="c3_ddr4_dq6"        loc="U8"/>
    <pin index="732"  name ="c3_ddr4_dq7"        loc="V5"/>
    <pin index="733"  name ="c3_ddr4_dq8"        loc="AA1"/>
    <pin index="734"  name ="c3_ddr4_dq9"        loc="AD2"/>
	<pin index="735"  name ="c3_ddr4_dq10"       loc="AB1"/>
    <pin index="736"  name ="c3_ddr4_dq11"       loc="AD3"/>
    <pin index="737"  name ="c3_ddr4_dq12"       loc="AA2"/>
    <pin index="738"  name ="c3_ddr4_dq13"       loc="AE1"/>
    <pin index="739"  name ="c3_ddr4_dq14"       loc="Y1"/>
    <pin index="740"  name ="c3_ddr4_dq15"       loc="AE2"/>
    <pin index="741"  name ="c3_ddr4_dq16"       loc="AA3"/>
    <pin index="742"  name ="c3_ddr4_dq17"       loc="AB6"/>
    <pin index="743"  name ="c3_ddr4_dq18"       loc="AA6"/>
    <pin index="744"  name ="c3_ddr4_dq19"       loc="AD4"/>
    <pin index="745"  name ="c3_ddr4_dq20"       loc="AA4"/>
    <pin index="746"  name ="c3_ddr4_dq21"       loc="AE5"/>
    <pin index="747"  name ="c3_ddr4_dq22"       loc="AF4"/>
    <pin index="748"  name ="c3_ddr4_dq23"       loc="AE4"/>
    <pin index="749"  name ="c3_ddr4_dq24"       loc="U3"/>
    <pin index="750"  name ="c3_ddr4_dq25"       loc="V1"/>
    <pin index="751"  name ="c3_ddr4_dq26"       loc="W4"/>
    <pin index="752"  name ="c3_ddr4_dq27"       loc="W2"/>
    <pin index="753"  name ="c3_ddr4_dq28"       loc="U4"/>
    <pin index="754"  name ="c3_ddr4_dq29"       loc="W3"/>
    <pin index="755"  name ="c3_ddr4_dq30"       loc="Y4"/>
    <pin index="756"  name ="c3_ddr4_dq31"       loc="Y2"/>
    <pin index="757"  name ="c3_ddr4_dq32"       loc="N1"/>
    <pin index="758"  name ="c3_ddr4_dq33"       loc="P3"/>
	<pin index="759"  name ="c3_ddr4_dq34"       loc="P2"/>
    <pin index="760"  name ="c3_ddr4_dq35"       loc="T4"/>
    <pin index="761"  name ="c3_ddr4_dq36"       loc="N2"/>
    <pin index="762"  name ="c3_ddr4_dq37"       loc="R4"/>
    <pin index="763"  name ="c3_ddr4_dq38"       loc="N3"/>
    <pin index="764"  name ="c3_ddr4_dq39"       loc="P4"/>
    <pin index="765"  name ="c3_ddr4_dq40"       loc="H7"/>
    <pin index="766"  name ="c3_ddr4_dq41"       loc="L6"/>
    <pin index="767"  name ="c3_ddr4_dq42"       loc="J5"/>
    <pin index="768"  name ="c3_ddr4_dq43"       loc="L7"/>
    <pin index="769"  name ="c3_ddr4_dq44"       loc="G8"/>
    <pin index="770"  name ="c3_ddr4_dq45"       loc="M6"/>
    <pin index="771"  name ="c3_ddr4_dq46"       loc="J4"/>
    <pin index="772"  name ="c3_ddr4_dq47"       loc="M5"/>
    <pin index="773"  name ="c3_ddr4_dq48"       loc="J3"/>
    <pin index="774"  name ="c3_ddr4_dq49"       loc="L3"/>
    <pin index="775"  name ="c3_ddr4_dq50"       loc="K2"/>
    <pin index="776"  name ="c3_ddr4_dq51"       loc="M3"/>
    <pin index="777"  name ="c3_ddr4_dq52"       loc="J2"/>
    <pin index="778"  name ="c3_ddr4_dq53"       loc="M4"/>
    <pin index="779"  name ="c3_ddr4_dq54"       loc="K1"/>
    <pin index="780"  name ="c3_ddr4_dq55"       loc="L2"/>
    <pin index="781"  name ="c3_ddr4_dq56"       loc="V11"/>
    <pin index="782"  name ="c3_ddr4_dq57"       loc="Y13"/>
    <pin index="783"  name ="c3_ddr4_dq58"       loc="U10"/>
    <pin index="784"  name ="c3_ddr4_dq59"       loc="Y12"/>
    <pin index="785"  name ="c3_ddr4_dq60"       loc="U13"/>
    <pin index="786"  name ="c3_ddr4_dq61"       loc="W9"/>
    <pin index="787"  name ="c3_ddr4_dq62"       loc="U12"/>
    <pin index="788"  name ="c3_ddr4_dq63"       loc="Y10"/>
    <pin index="789"  name ="c3_ddr4_dq64"       loc="G10"/>
    <pin index="790"  name ="c3_ddr4_dq65"       loc="L12"/>
    <pin index="791"  name ="c3_ddr4_dq66"       loc="G9"/>
    <pin index="792"  name ="c3_ddr4_dq67"       loc="K11"/>
    <pin index="793"  name ="c3_ddr4_dq68"       loc="G11"/>
    <pin index="794"  name ="c3_ddr4_dq69"       loc="L11"/>
    <pin index="795"  name ="c3_ddr4_dq70"       loc="H12"/>
    <pin index="796"  name ="c3_ddr4_dq71"       loc="L10"/>
	<pin index="797"  name ="c3_ddr4_dqs_c0"     loc="U7"/>
	<pin index="798"  name ="c3_ddr4_dqs_c1"     loc="AC3"/>
	<pin index="799"  name ="c3_ddr4_dqs_c2"     loc="AB5"/>
	<pin index="800"  name ="c3_ddr4_dqs_c3"     loc="U1"/>
	<pin index="801"  name ="c3_ddr4_dqs_c4"     loc="T3"/>
	<pin index="802"  name ="c3_ddr4_dqs_c5"     loc="K5"/>
	<pin index="803"  name ="c3_ddr4_dqs_c6"     loc="L1"/>
	<pin index="804"  name ="c3_ddr4_dqs_c7"     loc="W13"/>
	<pin index="805"  name ="c3_ddr4_dqs_c8"     loc="J10"/>
    <pin index="806"  name ="c3_ddr4_dqs_t0"     loc="U6"/>
    <pin index="807"  name ="c3_ddr4_dqs_t1"     loc="AB3"/>
    <pin index="808"  name ="c3_ddr4_dqs_t2"     loc="AB4"/>
    <pin index="809"  name ="c3_ddr4_dqs_t3"     loc="T1"/>
    <pin index="810"  name ="c3_ddr4_dqs_t4"     loc="T2"/>
	<pin index="811"  name ="c3_ddr4_dqs_t5"     loc="K6"/>
	<pin index="812"  name ="c3_ddr4_dqs_t6"     loc="M1"/>
	<pin index="813"  name ="c3_ddr4_dqs_t7"     loc="V12"/>
	<pin index="814"  name ="c3_ddr4_dqs_t8"     loc="H10"/>
	<pin index="815"  name ="c3_ddr4_dm_dbi_n0"  loc="W8"/>
    <pin index="816"  name ="c3_ddr4_dm_dbi_n1"  loc="AC2"/>
	<pin index="817"  name ="c3_ddr4_dm_dbi_n2"  loc="AD5"/>
    <pin index="818"  name ="c3_ddr4_dm_dbi_n3"  loc="V2"/>
	<pin index="819"  name ="c3_ddr4_dm_dbi_n4"  loc="R1"/>
    <pin index="820"  name ="c3_ddr4_dm_dbi_n5"  loc="K7"/>
	<pin index="821"  name ="c3_ddr4_dm_dbi_n6"  loc="K4"/>
    <pin index="822"  name ="c3_ddr4_dm_dbi_n7"  loc="W11"/>
	<pin index="823"  name ="c3_ddr4_dm_dbi_n8"  loc="J12"/>
    <pin index="824"  name ="c3_ddr4_odt0"       loc="AE13"/>
    <pin index="825"  name ="c3_ddr4_reset_n"    loc="R7"  iostandard="LVCMOS12"   drive="8"/>
	<pin index="826"  name ="c3_ddr4_parity"     loc="AF9"/>
	<pin index="827"  name ="c3_ddr4_alert_n"    loc="T6"/>



    <pin index="1000" name ="pcie_rx0_n"      loc="AC42"/>
    <pin index="1001" name ="pcie_rx0_p"      loc="AC41"/>
    <pin index="1002" name ="pcie_rx1_n"      loc="AA42"/>
    <pin index="1003" name ="pcie_rx1_p"      loc="AA41"/>
    <pin index="1004" name ="pcie_rx2_n"      loc="W42"/>
    <pin index="1005" name ="pcie_rx2_p"      loc="W41"/>	
    <pin index="1006" name ="pcie_rx3_n"      loc="U42"/>
    <pin index="1007" name ="pcie_rx3_p"      loc="U41"/>
    <pin index="1008" name ="pcie_rx4_n"      loc="R42"/>
    <pin index="1009" name ="pcie_rx4_p"      loc="R41"/>	
    <pin index="1010" name ="pcie_rx5_n"      loc="N42"/>
    <pin index="1011" name ="pcie_rx5_p"      loc="N41"/>	
    <pin index="1012" name ="pcie_rx6_n"      loc="L42"/>
    <pin index="1013" name ="pcie_rx6_p"      loc="L41"/>	
    <pin index="1014" name ="pcie_rx7_n"      loc="K40"/>
    <pin index="1015" name ="pcie_rx7_p"      loc="K39"/>	
	<pin index="1016" name ="pcie_rx8_n"      loc="J42"/>
	<pin index="1017" name ="pcie_rx8_p"      loc="J41"/>	
    <pin index="1018" name ="pcie_rx9_n"      loc="H40"/>
    <pin index="1019" name ="pcie_rx9_p"      loc="H39"/>	
    <pin index="1020" name ="pcie_rx10_n"     loc="G42"/>
    <pin index="1021" name ="pcie_rx10_p"     loc="G41"/>	
    <pin index="1022" name ="pcie_rx11_n"     loc="F40"/>
    <pin index="1023" name ="pcie_rx11_p"     loc="F39"/>	
    <pin index="1024" name ="pcie_rx12_n"     loc="E42"/>
    <pin index="1025" name ="pcie_rx12_p"     loc="E41"/>	
    <pin index="1026" name ="pcie_rx13_n"     loc="D40"/>
    <pin index="1027" name ="pcie_rx13_p"     loc="D39"/>	
    <pin index="1028" name ="pcie_rx14_n"     loc="C42"/>
    <pin index="1029" name ="pcie_rx14_p"     loc="C41"/>
    <pin index="1030" name ="pcie_rx15_n"     loc="B40"/>	
    <pin index="1031" name ="pcie_rx15_p"     loc="B39"/>		
    <pin index="1032" name ="pcie_tx0_n"      loc="AB39"/>
    <pin index="1033" name ="pcie_tx0_p"      loc="AB38"/>	
    <pin index="1034" name ="pcie_tx1_n"      loc="AA37"/>
    <pin index="1035" name ="pcie_tx1_p"      loc="AA36"/>	
    <pin index="1036" name ="pcie_tx2_n"      loc="Y39"/>
    <pin index="1037" name ="pcie_tx2_p"      loc="Y38"/>    
	<pin index="1038" name ="pcie_tx3_n"      loc="V39"/>
	<pin index="1039" name ="pcie_tx3_p"      loc="V38"/>   
	<pin index="1040" name ="pcie_tx4_n"      loc="T39"/>
	<pin index="1041" name ="pcie_tx4_p"      loc="T38"/>    
	<pin index="1042" name ="pcie_tx5_n"      loc="P39"/>
	<pin index="1043" name ="pcie_tx5_p"      loc="P38"/>   
    <pin index="1044" name ="pcie_tx6_n"      loc="M39"/>
    <pin index="1045" name ="pcie_tx6_p"      loc="M38"/>    
	<pin index="1046" name ="pcie_tx7_n"      loc="J37"/>
	<pin index="1047" name ="pcie_tx7_p"      loc="J36"/>
	<pin index="1048" name ="pcie_tx8_n"      loc="H35"/>
	<pin index="1049" name ="pcie_tx8_p"      loc="H34"/>   
    <pin index="1050" name ="pcie_tx9_n"      loc="G37"/>
    <pin index="1051" name ="pcie_tx9_p"      loc="G36"/>    
	<pin index="1052" name ="pcie_tx10_n"     loc="F35"/>
	<pin index="1053" name ="pcie_tx10_p"     loc="F34"/>    
	<pin index="1054" name ="pcie_tx11_n"     loc="E37"/>
	<pin index="1055" name ="pcie_tx11_p"     loc="E36"/> 
	<pin index="1056" name ="pcie_tx12_n"     loc="D35"/>
	<pin index="1057" name ="pcie_tx12_p"     loc="D34"/>    
	<pin index="1058" name ="pcie_tx13_n"     loc="C37"/>
	<pin index="1059" name ="pcie_tx13_p"     loc="C36"/>    
	<pin index="1060" name ="pcie_tx14_n"     loc="B35"/>
	<pin index="1061" name ="pcie_tx14_p"     loc="B34"/>    
	<pin index="1062" name ="pcie_tx15_n"     loc="B40"/>	
	<pin index="1063" name ="pcie_tx15_p"     loc="B39"/>		
	
  	<pin index="1064" name ="pcie_refclk_0_n" loc="AB35"/>
    <pin index="1065" name ="pcie_refclk_0_p" loc="AB34"/>	
    <pin index="1066" name ="pcie_refclk_1_n" loc="W37"/>
    <pin index="1067" name ="pcie_refclk_1_p" loc="W36"/>
  	<pin index="1068" name ="pcie_refclk_2_n" loc="R37"/>
    <pin index="1069" name ="pcie_refclk_2_p" loc="R36"/>	
    <pin index="1070" name ="pcie_refclk_3_n" loc="L37"/>
    <pin index="1071" name ="pcie_refclk_3_p" loc="L36"/>	
  	<pin index="1072" name ="pcie_sysclk_0_n" loc="Y35"/>
    <pin index="1073" name ="pcie_sysclk_0_p" loc="Y34"/>	
    <pin index="1074" name ="pcie_sysclk_1_n" loc="U37"/>
    <pin index="1075" name ="pcie_sysclk_1_p" loc="U36"/>	
  	<pin index="1076" name ="pcie_sysclk_2_n" loc="N37"/>
    <pin index="1077" name ="pcie_sysclk_2_p" loc="N36"/>	
    <pin index="1078" name ="pcie_sysclk_3_n" loc="K35"/>
    <pin index="1079" name ="pcie_sysclk_3_p" loc="K34"/>		
	

    <pin index="1100" name ="qsfp0_TX_N0"     loc="F1"/>
    <pin index="1101" name ="qsfp0_TX_P0"     loc="G1"/>
    <pin index="1102" name ="qsfp0_RX_N0"     loc="C2"/>
    <pin index="1103" name ="qsfp0_RX_P0"     loc="D2"/>
    <pin index="1104" name ="qsfp0_TX_N1"     loc="F3"/>
    <pin index="1105" name ="qsfp0_TX_P1"     loc="G3"/>
    <pin index="1106" name ="qsfp0_RX_N1"     loc="A3"/>
    <pin index="1107" name ="qsfp0_RX_P1"     loc="B3"/>
    <pin index="1108" name ="qsfp0_TX_N2"     loc="F5"/>
    <pin index="1109" name ="qsfp0_TX_P2"     loc="G5"/>
    <pin index="1110" name ="qsfp0_RX_N2"     loc="C4"/>
    <pin index="1111" name ="qsfp0_RX_P2"     loc="D4"/>
    <pin index="1112" name ="qsfp0_TX_N3"     loc="F5"/>
    <pin index="1113" name ="qsfp0_TX_P3"     loc="G5"/>
    <pin index="1114" name ="qsfp0_RX_N3"     loc="A5"/>
    <pin index="1115" name ="qsfp0_RX_P3"     loc="B5"/>
	<pin index="1116" name ="qsfp0_161mhz_n" loc="A15"/>
    <pin index="1117" name ="qsfp0_161mhz_p" loc="B15"/>
	
	<pin index="1200" name ="qsfp1_TX_N0"     loc="G49"/>
    <pin index="1201" name ="qsfp1_TX_P0"     loc="G48"/>
    <pin index="1202" name ="qsfp1_RX_N0"     loc="G54"/>
    <pin index="1203" name ="qsfp1_RX_P0"     loc="G53"/>
    <pin index="1204" name ="qsfp1_TX_N1"     loc="E49"/>
    <pin index="1205" name ="qsfp1_TX_P1"     loc="E48"/>
    <pin index="1206" name ="qsfp1_RX_N1"     loc="F52"/>
    <pin index="1207" name ="qsfp1_RX_P1"     loc="F51"/>
    <pin index="1208" name ="qsfp1_TX_N2"     loc="C49"/>
    <pin index="1209" name ="qsfp1_TX_P2"     loc="C48"/>
    <pin index="1210" name ="qsfp1_RX_N2"     loc="E54"/>
    <pin index="1211" name ="qsfp1_RX_P2"     loc="E53"/>
    <pin index="1212" name ="qsfp1_TX_N3"     loc="A50"/>
    <pin index="1213" name ="qsfp1_TX_P3"     loc="A49"/>
    <pin index="1214" name ="qsfp1_RX_N3"     loc="D52"/>
    <pin index="1215" name ="qsfp1_RX_P3"     loc="D51"/>
	<pin index="1216" name ="qsfp1_161mhz_n"  loc="M43"/>
    <pin index="1217" name ="qsfp1_161mhz_p"  loc="M42"/>		

  
  </pins>
  
</part_info>
